{"stats":{"minecraft:custom":{"minecraft:jump":146,"minecraft:time_since_rest":21899,"minecraft:crouch_one_cm":64,"minecraft:leave_game":1,"minecraft:sprint_one_cm":22619,"minecraft:play_time":21899,"minecraft:time_since_death":21899,"minecraft:walk_one_cm":9614,"minecraft:sneak_time":651,"minecraft:total_world_time":40729,"minecraft:interact_with_crafting_table":4,"minecraft:fly_one_cm":424478,"minecraft:horse_one_cm":9287},"minecraft:crafted":{"magistuarmory:face_helmet":2},"minecraft:used":{"minecraft:spyglass":4,"minecraft:stripped_spruce_wood":1,"minecraft:armor_stand":4}},"DataVersion":3578}